horiba_sdk/__init__.py
horiba_sdk/communication/__init__.py
horiba_sdk/communication/abstract_communicator.py
horiba_sdk/communication/communication_exception.py
horiba_sdk/communication/messages.py
horiba_sdk/communication/websocket_communicator.py
horiba_sdk/core/__init__.py
horiba_sdk/core/acquisition_format.py
horiba_sdk/core/clean_count_mode.py
horiba_sdk/core/resolution.py
horiba_sdk/core/stitching/__init__.py
horiba_sdk/core/stitching/labspec6_spectra_stitch.py
horiba_sdk/core/stitching/linear_spectra_stitch.py
horiba_sdk/core/stitching/simple_cut_spectra_stitch.py
horiba_sdk/core/stitching/spectra_stitch.py
horiba_sdk/core/stitching/y_displacement_spectra_stitch.py
horiba_sdk/core/timer_resolution.py
horiba_sdk/core/trigger_input_polarity.py
horiba_sdk/core/x_axis_conversion_type.py
horiba_sdk/devices/__init__.py
horiba_sdk/devices/abstract_device_discovery.py
horiba_sdk/devices/abstract_device_manager.py
horiba_sdk/devices/ccd_discovery.py
horiba_sdk/devices/device_manager.py
horiba_sdk/devices/fake_device_manager.py
horiba_sdk/devices/fake_icl_server.py
horiba_sdk/devices/fake_responses/ccd.json
horiba_sdk/devices/fake_responses/icl.json
horiba_sdk/devices/fake_responses/monochromator.json
horiba_sdk/devices/fake_responses/spectracq3.json
horiba_sdk/devices/monochromator_discovery.py
horiba_sdk/devices/single_devices/__init__.py
horiba_sdk/devices/single_devices/abstract_device.py
horiba_sdk/devices/single_devices/ccd.py
horiba_sdk/devices/single_devices/monochromator.py
horiba_sdk/devices/single_devices/spectracq3.py
horiba_sdk/devices/spectracq3_discovery.py
horiba_sdk/icl_error/__init__.py
horiba_sdk/icl_error/abstract_error.py
horiba_sdk/icl_error/abstract_error_db.py
horiba_sdk/icl_error/error_list.json
horiba_sdk/icl_error/icl_error.py
horiba_sdk/icl_error/icl_error_db.py
horiba_sdk-1.0.0.dist-info/LICENSE
horiba_sdk-1.0.0.dist-info/METADATA
horiba_sdk-1.0.0.dist-info/WHEEL
horiba_sdk-1.0.0.dist-info/RECORD
