Metadata-Version: 2.1
Name: horiba-sdk
Version: 1.0.0
Summary: 'horiba-sdk' is a package that provides source code for the development with Horiba devices
Home-page: https://github.com/HORIBAEzSpecSDK/python-sdk
License: MIT
Keywords: Horiba,SDK
Author: HORIBA Instruments, Inc.
Author-email: EZSpec-SDK.us@horiba.com
Requires-Python: >=3.9,<4
Classifier: Development Status :: 3 - Alpha
Classifier: Intended Audience :: Developers
Classifier: License :: OSI Approved :: MIT License
Classifier: Operating System :: OS Independent
Classifier: Programming Language :: Python :: 3
Classifier: Programming Language :: Python :: 3.9
Classifier: Programming Language :: Python :: 3.10
Classifier: Programming Language :: Python :: 3.11
Classifier: Topic :: Software Development :: Libraries :: Python Modules
Requires-Dist: loguru (>=0.7.2,<0.8.0)
Requires-Dist: overrides (>=7.4.0,<8.0.0)
Requires-Dist: pint (>=0.23,<0.24)
Requires-Dist: psutil (>=5.9.7,<6.0.0)
Requires-Dist: pydantic (>=2.10.6,<3.0.0)
Requires-Dist: websockets (>=12.0,<13.0)
Project-URL: Repository, https://github.com/HORIBAEzSpecSDK/python-sdk
